fanucpy/__init__.py
fanucpy/calibration.py
fanucpy/robot.py
fanucpy/robotapp.py
fanucpy/transformations.py
fanucpy-0.1.14.dist-info/LICENSE
fanucpy-0.1.14.dist-info/METADATA
fanucpy-0.1.14.dist-info/WHEEL
fanucpy-0.1.14.dist-info/RECORD
