Metadata-Version: 2.1
Name: fanucpy
Version: 0.1.14
Summary: Python package for FANUC industrial robots
Home-page: https://github.com/torayeff/fanucpy
License: Apache-2.0
Keywords: fanuc,industrial robot,robotic apps
Author: Agajan Torayev
Author-email: torayeff@gmail.com
Requires-Python: >=3.8
Classifier: License :: OSI Approved :: Apache Software License
Classifier: Programming Language :: Python :: 3
Classifier: Programming Language :: Python :: 3.8
Classifier: Programming Language :: Python :: 3.9
Classifier: Programming Language :: Python :: 3.10
Classifier: Programming Language :: Python :: 3.11
Classifier: Programming Language :: Python :: 3.12
Requires-Dist: numpy (>=1.24.0,<2.0.0)
Requires-Dist: scipy (>=1.10.0,<2.0.0)
Project-URL: Repository, https://github.com/torayeff/fanucpy
